[
  {
    "id": "minatogawa-shrine-summer-festival-2026",
    "title": "湊川神社 夏まつり～献燈祭・菊水天神祭～",
    "startAt": "2026-08-22T17:00:00+09:00",
    "endAt": "2026-08-26T21:30:00+09:00",
    "showEachDay": true,
    "broadcast": "現地イベント",
    "category": "祭り",
    "area": "神戸・中央区",
    "inPersonEvent": true,
    "liveReason": "湊川神社公式で8月22日から26日までの5日間開催が確認できる神戸の夏の風物詩。提灯、ねぶた灯籠、屋台、奉納行事などで夕方から夜に来場が集中する",
    "trafficReason": "夏まつり期間中は境内駐車場が利用できず、神戸駅・高速神戸駅周辺の徒歩移動、近隣駐車場、夜間の帰宅動線への影響が見込まれる",
    "nationalReach": 1,
    "liveUrgency": 2,
    "accessibility": 3,
    "buzz": 2,
    "significance": 3,
    "impactLevelOverride": "中",
    "officialConfirmed": true,
    "sources": [
      {
        "title": "湊川神社 夏まつり～献燈祭・菊水天神祭～",
        "url": "https://www.minatogawajinja.or.jp/natumaturi/"
      },
      {
        "title": "湊川神社 祭典・行事等一覧",
        "url": "https://www.minatogawajinja.or.jp/event/"
      }
    ]
  },
  {
    "id": "kaijinja-summer-festival-2026",
    "title": "海神社 夏祭り",
    "startAt": "2026-07-18T17:00:00+09:00",
    "endAt": "2026-07-20T21:00:00+09:00",
    "showEachDay": true,
    "broadcast": "現地イベント",
    "category": "祭り",
    "area": "神戸・垂水",
    "inPersonEvent": true,
    "liveReason": "海神社公式で7月18日から20日までの3日間開催が確認できる。JR・山陽垂水駅から徒歩1分の地元祭りで、勤務先に近く来街者が集中する",
    "trafficReason": "夏祭り期間中は17時頃から交通規制が予定され、垂水駅周辺の人流・帰宅動線・買い回りに直接かつ大きな影響が見込まれる",
    "nationalReach": 1,
    "liveUrgency": 3,
    "accessibility": 3,
    "buzz": 2,
    "significance": 3,
    "impactLevelOverride": "大",
    "officialConfirmed": true,
    "sources": [
      {
        "title": "海神社 令和8年夏祭り・交通規制のお知らせ",
        "url": "https://kaijinjya.jp/"
      },
      {
        "title": "海神社駐車場休業日について",
        "url": "https://kaijinjya.jp/news/251222-3"
      }
    ]
  },
  {
    "id": "sumo-july-basho-2026-opening-days",
    "title": "大相撲七月場所 序盤",
    "startAt": "2026-07-12T15:05:00+09:00",
    "endAt": "2026-07-13T18:00:00+09:00",
    "broadcast": "NHK総合・NHK BSなど（番組表確認）",
    "category": "スポーツ中継",
    "area": "全国",
    "liveReason": "日本相撲協会公式で七月場所が7月12日から26日までIGアリーナ開催と確認できる。初日から序盤は新会場・番付・上位陣の結果確認で話題化する可能性がある",
    "trafficReason": "午後から夕方のテレビ視聴・結果確認が一部で起きるが、序盤のため全国的な客足低下は小から中程度に抑えて確認する",
    "nationalReach": 2,
    "liveUrgency": 1,
    "accessibility": 3,
    "buzz": 1,
    "significance": 1,
    "impactLevelOverride": "小",
    "officialConfirmed": true,
    "sources": [
      {
        "title": "日本相撲協会 2026 Grand Tournament Schedule",
        "url": "https://www.sumo.or.jp/EnTicket/year_schedule/"
      },
      {
        "title": "NHK 大相撲中継",
        "url": "https://www.nhk.jp/p/ts/JY7XMMG241/"
      },
      {
        "title": "2026 in sumo",
        "url": "https://en.wikipedia.org/wiki/2026_in_sumo"
      }
    ]
  },
  {
    "id": "wimbledon-2026-mens-final",
    "title": "ウィンブルドン2026 男子シングルス決勝",
    "startAt": "2026-07-13T00:00:00+09:00",
    "endAt": "2026-07-13T03:30:00+09:00",
    "broadcast": "海外: ESPN・BBCなど、日本国内放送・配信は番組表確認",
    "category": "スポーツ中継",
    "area": "全国",
    "liveReason": "四大大会の男子決勝で、Jannik SinnerがAlexander Zverevを破って連覇した試合。日本時間では前夜深夜から未明にかかり、テニスファンのリアルタイム視聴と朝の結果確認が起きやすい",
    "trafficReason": "深夜視聴後の睡眠不足や朝の結果確認で、7月13日午前から昼の外出開始が遅れる可能性を確認する。日本選手の本戦決勝ではないため影響は中程度に抑える",
    "nationalReach": 2,
    "liveUrgency": 2,
    "accessibility": 1,
    "buzz": 2,
    "significance": 3,
    "officialConfirmed": false,
    "sources": [
      {
        "title": "AP Jannik Sinner beats Alexander Zverev to win Wimbledon again",
        "url": "https://apnews.com/article/e3e69ad0a4900b484b0eccd2751923e0"
      },
      {
        "title": "The Guardian Sinner caps Wimbledon fortnight",
        "url": "https://www.theguardian.com/sport/2026/jul/12/jannik-sinner-wimbledon-2026-alexander-zverev-arthur-fery-tennis"
      },
      {
        "title": "New York Post Wimbledon 2026 men's final watch guide",
        "url": "https://nypost.com/2026/07/12/sports/how-to-watch-zverev-sinner-in-wimbledon-2026-final-for-free/"
      }
    ]
  },
  {
    "id": "mlb-home-run-derby-2026",
    "title": "MLBオールスターゲーム2026 ホームランダービー",
    "startAt": "2026-07-14T09:00:00+09:00",
    "endAt": "2026-07-14T12:00:00+09:00",
    "broadcast": "Netflix（日本時間9:00開始、特別番組は8:00開始）",
    "category": "スポーツ中継",
    "area": "全国",
    "liveReason": "MLB公式で村上宗隆選手を含む8選手の出場と、日本時間9:00からNetflixでのライブ配信が確定。日本時間の午前帯に野球ファンのリアルタイム視聴とSNS確認が起きやすい",
    "trafficReason": "午前の在宅視聴・SNS確認で外出開始が遅れる可能性はあるが、Netflix配信のため地上波中継より視聴範囲は限定的として中程度に扱う",
    "nationalReach": 2,
    "liveUrgency": 2,
    "accessibility": 2,
    "buzz": 3,
    "significance": 2,
    "officialConfirmed": true,
    "sources": [
      {
        "title": "MLB公式 2026 Home Run Derby出場者・配信情報",
        "url": "https://www.mlb.com/news/2026-mlb-home-run-derby-participants"
      },
      {
        "title": "MLB公式 All-Star Game 2026",
        "url": "https://www.mlb.com/all-star"
      },
      {
        "title": "New York Post Juan Soto Home Run Derby report",
        "url": "https://nypost.com/2026/07/11/sports/mets-juan-soto-explains-why-he-decided-to-skip-home-run-derby/"
      }
    ]
  },
  {
    "id": "gion-matsuri-2026-saki-yama",
    "title": "祇園祭 前祭 宵山",
    "startAt": "2026-07-14T18:00:00+09:00",
    "endAt": "2026-07-16T23:30:00+09:00",
    "broadcast": "現地イベント",
    "category": "祭り",
    "area": "京都",
    "inPersonEvent": true,
    "liveReason": "日本三大祭の一つとして全国認知があり、前祭の宵山期間は京都中心部の夜間人流が大きい",
    "trafficReason": "京都中心部の夜間人流・交通混雑が大きく、関西圏の外出先選択や帰宅動線に影響する可能性がある",
    "nationalReach": 3,
    "liveUrgency": 2,
    "accessibility": 1,
    "buzz": 2,
    "significance": 3,
    "impactLevelOverride": "中",
    "officialConfirmed": true,
    "sources": [
      {
        "title": "GionFestival.org Gion Festival overview",
        "url": "https://www.gionfestival.org/"
      },
      {
        "title": "京都観光Navi 祇園祭",
        "url": "https://ja.kyoto.travel/event/major/gion/"
      }
    ]
  },
  {
    "id": "fifa-world-cup-2026-semifinal-fra-esp",
    "title": "サッカーW杯 準決勝 FRA対ESP",
    "startAt": "2026-07-15T04:00:00+09:00",
    "endAt": "2026-07-15T06:30:00+09:00",
    "broadcast": "日本テレビ（生中継）・DAZN（無料ライブ／見逃し配信）・NHK BSプレミアム4K（7月15日21:00録画放送）",
    "category": "スポーツ中継",
    "area": "全国",
    "liveReason": "サッカーW杯準決勝。現地7月14日の準決勝で、公開報道でもFRA対ESPとして話題化している。日本時間は早朝だが、結果確認とハイライト視聴が朝の行動に影響しやすい",
    "trafficReason": "早朝リアルタイム視聴や起床直後の結果確認で、午前から昼の外出開始が遅れる可能性を確認する",
    "nationalReach": 3,
    "liveUrgency": 3,
    "accessibility": 3,
    "buzz": 3,
    "significance": 3,
    "officialConfirmed": true,
    "sources": [
      {
        "title": "FIFA World Cup 2026 Matches",
        "url": "https://www.fifa.com/en/tournaments/mens/worldcup/canadamexicousa2026/matches"
      },
      {
        "title": "GOAL フランス対スペイン 放送・配信予定",
        "url": "https://www.goal.com/jp/%E3%83%8B%E3%83%A5%E3%83%BC%E3%82%B9/when-france-spain-kickoff-time-broadcast-world-cup-2026/blt14fc5f0ba5ac14f6"
      },
      {
        "title": "The Guardian World Cup 2026 coverage",
        "url": "https://www.theguardian.com/football/2026/jul/12/argentina-switzerland-lionel-scaloni-england-semi-final"
      },
      {
        "title": "2026 FIFA World Cup broadcasting rights",
        "url": "https://en.wikipedia.org/wiki/2026_FIFA_World_Cup_broadcasting_rights"
      }
    ]
  },
  {
    "id": "mlb-all-star-game-2026",
    "title": "MLBオールスターゲーム2026 本戦",
    "startAt": "2026-07-15T09:00:00+09:00",
    "endAt": "2026-07-15T12:30:00+09:00",
    "broadcast": "TBS系列（9:00から生中継）・SPOTV NOW（無料ライブ配信）・米FOX",
    "category": "スポーツ中継",
    "area": "全国",
    "liveReason": "MLB公式で日本時間7月15日9:00開始が確認でき、TBS系列の生中継とSPOTV NOWの無料ライブ配信も確定。村上宗隆選手・山本由伸選手ら日本関連選手への注目が高く、午前帯のリアルタイム視聴とSNS確認が起きやすい",
    "trafficReason": "平日午前の地上波生中継・無料配信により、在宅視聴や結果確認で午前から昼の外出開始が遅れる可能性を確認する",
    "nationalReach": 3,
    "liveUrgency": 3,
    "accessibility": 3,
    "buzz": 3,
    "significance": 2,
    "officialConfirmed": true,
    "sources": [
      {
        "title": "MLB公式 2026オールスターのメンバー発表",
        "url": "https://www.mlb.com/ja/news/2026-mlb-all-star-rosters"
      },
      {
        "title": "TBSテレビ MLBオールスター2026",
        "url": "https://www.tbs.co.jp/tv/20260715_B595.html"
      },
      {
        "title": "SPOTV NOW MLBオールスター2026無料ライブ配信",
        "url": "https://prtimes.jp/main/html/rd/p/000000048.000075946.html"
      }
    ]
  },
  {
    "id": "fifa-world-cup-2026-semifinal-arg-eng",
    "title": "サッカーW杯 準決勝 ENG対ARG",
    "startAt": "2026-07-16T04:00:00+09:00",
    "endAt": "2026-07-16T06:30:00+09:00",
    "broadcast": "NHK総合・BSP4K（3:45から生放送）・NHK ONE・DAZN",
    "category": "スポーツ中継",
    "area": "全国",
    "liveReason": "サッカーW杯準決勝。ENG対ARGの歴史的対戦とメッシ出場で公開SNS・ニュースの注目が高まり、ARGが2–1で勝利して決勝進出。日本時間の深夜・早朝にリアルタイム視聴と起床後の結果確認が起きやすい",
    "trafficReason": "深夜・早朝のリアルタイム視聴や起床直後の結果・ハイライト確認で、午前から昼の外出開始が遅れる可能性を確認する",
    "nationalReach": 3,
    "liveUrgency": 3,
    "accessibility": 3,
    "buzz": 3,
    "significance": 3,
    "officialConfirmed": true,
    "sources": [
      {
        "title": "FIFA England v Argentina match preview",
        "url": "https://www.fifa.com/en/tournaments/mens/worldcup/canadamexicousa2026/articles/england-v-argentina-live-stream-team-news-tickets-and-more"
      },
      {
        "title": "NHK FIFAワールドカップ2026 決勝トーナメント放送試合",
        "url": "https://prtimes.jp/main/html/rd/p/000000074.000160617.html"
      },
      {
        "title": "AV Watch ENG対ARG 放送・配信予定",
        "url": "https://av.watch.impress.co.jp/docs/news/2125462.html"
      },
      {
        "title": "AP ARGがENGに2–1で勝利",
        "url": "https://apnews.com/article/2ae6a218ae88248db6565ffd13f60d38"
      }
    ]
  },
  {
    "id": "gion-matsuri-2026-saki-junko",
    "title": "祇園祭 前祭 山鉾巡行・神幸祭",
    "startAt": "2026-07-17T09:00:00+09:00",
    "endAt": "2026-07-17T21:00:00+09:00",
    "broadcast": "KBS京都（山鉾巡行 8:30〜11:30生中継）・京都観光Navi YouTube（混雑ライブカメラ）",
    "category": "祭り",
    "area": "京都",
    "inPersonEvent": true,
    "liveReason": "祇園祭の中心行事。山鉾巡行と神輿渡御で京都中心部に終日人流が集まり、全国ニュースでも扱われやすい",
    "trafficReason": "京都中心部の終日人流・交通規制・夕方以降の帰宅混雑が見込まれ、関西圏の外出先選択や帰宅動線に影響する可能性がある",
    "nationalReach": 3,
    "liveUrgency": 3,
    "accessibility": 1,
    "buzz": 3,
    "significance": 3,
    "impactLevelOverride": "中",
    "officialConfirmed": true,
    "sources": [
      {
        "title": "GionFestival.org Gion Festival overview",
        "url": "https://www.gionfestival.org/"
      },
      {
        "title": "京都観光Navi 祇園祭",
        "url": "https://ja.kyoto.travel/event/major/gion/"
      },
      {
        "title": "KBS京都 生中継 祇園祭山鉾巡行・前祭2026",
        "url": "https://www.kbs-kyoto.co.jp/info/sp_prog/sp_146520.htm"
      },
      {
        "title": "京都市交通局 祇園祭に伴う臨時増発・経路変更",
        "url": "https://www.city.kyoto.lg.jp/kotsu/page/0000355768.html"
      }
    ]
  },
  {
    "id": "ongaku-no-hi-2026",
    "title": "音楽の日2026",
    "startAt": "2026-07-18T14:00:00+09:00",
    "endAt": "2026-07-18T22:00:00+09:00",
    "broadcast": "TBS系列（14:00から8時間生放送）",
    "category": "音楽特番",
    "area": "全国",
    "liveReason": "TBS公式で7月18日14時から8時間生放送と総勢80組のタイムテーブルが確認できる大型音楽特番。出演時間に合わせたリアルタイム視聴と番組公式SNSで当日の話題化が起きやすい",
    "trafficReason": "午後から夜にかけて長時間の生放送が続くため、目当ての出演時間に合わせた早めの帰宅や在宅視聴で客足が弱まる可能性を確認する",
    "nationalReach": 3,
    "liveUrgency": 2,
    "accessibility": 3,
    "buzz": 2,
    "significance": 1,
    "officialConfirmed": true,
    "sources": [
      {
        "title": "TBSテレビ 音楽の日2026 放送概要",
        "url": "https://www.tbs.co.jp/ongakunohi/articles/20260601.html"
      },
      {
        "title": "TBS 音楽の日2026 タイムテーブル",
        "url": "https://www.tbs.co.jp/ongakunohi/timetable/"
      }
    ]
  },
  {
    "id": "fifa-world-cup-2026-third-place",
    "title": "サッカーW杯 3位決定戦 FRA対ENG",
    "startAt": "2026-07-19T06:00:00+09:00",
    "endAt": "2026-07-19T08:30:00+09:00",
    "broadcast": "NHK総合・BSP4K・NHK ONE（5:45から生放送）・DAZN（無料ライブ配信）",
    "category": "スポーツ中継",
    "area": "全国",
    "liveReason": "FIFA公式でサッカーW杯3位決定戦の対戦カードがFRA対ENGに確定。NHK地上波・BSP4K・NHK ONEの生放送とDAZN無料配信があり、週末早朝のリアルタイム視聴・結果確認が起きやすい",
    "trafficReason": "5:45からの放送・配信と6:00キックオフをリアルタイム視聴した後、日曜午前から昼の外出開始が遅れる可能性を確認する",
    "nationalReach": 3,
    "liveUrgency": 2,
    "accessibility": 3,
    "buzz": 2,
    "significance": 2,
    "officialConfirmed": true,
    "sources": [
      {
        "title": "FIFA サッカーW杯2026 3位決定戦 FRA対ENG",
        "url": "https://www.fifa.com/fr/tournaments/mens/worldcup/canadamexicousa2026/articles/france-angleterre-match-troisieme-place-presentation-diffusion-infos-equipes-billettere"
      },
      {
        "title": "NHK FIFAワールドカップ2026 決勝トーナメント放送試合",
        "url": "https://prtimes.jp/main/html/rd/p/000000074.000160617.html"
      },
      {
        "title": "AV Watch W杯3位決定戦・決勝の放送配信予定",
        "url": "https://av.watch.impress.co.jp/docs/news/2125462.html"
      }
    ]
  },
  {
    "id": "fifa-world-cup-2026-final",
    "title": "サッカーW杯 決勝 ESP対ARG",
    "startAt": "2026-07-20T04:00:00+09:00",
    "endAt": "2026-07-20T06:45:00+09:00",
    "broadcast": "NHK総合・BSP4K・NHK ONE（3:00から生放送、4:00キックオフ）・DAZN",
    "category": "スポーツ中継",
    "area": "全国",
    "liveReason": "サッカーW杯 決勝 ESP対ARG。世界最大級のスポーツイベントで、海の日の祝日早朝に重なり、NHKとDAZNでのリアルタイム視聴と結果確認の動機が強い",
    "trafficReason": "深夜・早朝視聴後の睡眠不足、祝日午前の外出開始遅れ、SNS・ニュース確認による行動変化を確認する",
    "nationalReach": 3,
    "liveUrgency": 3,
    "accessibility": 3,
    "buzz": 3,
    "significance": 3,
    "officialConfirmed": true,
    "sources": [
      {
        "title": "FIFA World Cup 2026 Matches",
        "url": "https://www.fifa.com/en/tournaments/mens/worldcup/canadamexicousa2026/matches"
      },
      {
        "title": "AP World Cup final ticket report",
        "url": "https://apnews.com/article/1eb6731d9cb7dc1bde02b41c9992174c"
      },
      {
        "title": "NHK FIFAワールドカップ2026 決勝・出演者のお知らせ",
        "url": "https://prtimes.jp/main/html/rd/p/000000084.000160617.html"
      }
    ]
  },
  {
    "id": "gion-matsuri-2026-ato-yama",
    "title": "祇園祭 後祭 宵山",
    "startAt": "2026-07-21T18:00:00+09:00",
    "endAt": "2026-07-23T23:00:00+09:00",
    "broadcast": "現地イベント",
    "category": "祭り",
    "area": "京都",
    "inPersonEvent": true,
    "liveReason": "祇園祭の後祭宵山。前祭より規模は抑えめだが、京都中心部の夜間人流と観光回遊が発生する",
    "trafficReason": "京都中心部の夜間人流・帰宅混雑が関西圏の外出先選択や移動時間に影響する可能性がある",
    "nationalReach": 2,
    "liveUrgency": 2,
    "accessibility": 1,
    "buzz": 2,
    "significance": 2,
    "impactLevelOverride": "中",
    "officialConfirmed": true,
    "sources": [
      {
        "title": "GionFestival.org Gion Festival overview",
        "url": "https://www.gionfestival.org/"
      },
      {
        "title": "京都観光Navi 祇園祭",
        "url": "https://ja.kyoto.travel/event/major/gion/"
      }
    ]
  },
  {
    "id": "vnl-women-2026-final-round",
    "title": "VNL女子2026 ファイナルラウンド 準々決勝 JPN対BRA",
    "startAt": "2026-07-22T20:30:00+09:00",
    "endAt": "2026-07-22T23:00:00+09:00",
    "broadcast": "VBTV・TBS系列（日本戦の追加放送枠は公式番組表で直前確認）",
    "category": "スポーツ中継",
    "area": "全国",
    "liveReason": "Volleyball World公式で日本の決勝ラウンド進出と、7月22日20時30分開始の準々決勝JPN対BRAが確定。日本代表の一発勝負でリアルタイム視聴とSNS確認の動機が強い",
    "trafficReason": "平日夜の試合で、開始2時間前から帰宅・視聴準備が起き、試合中は外出や買い物を控える可能性を確認する",
    "nationalReach": 3,
    "liveUrgency": 3,
    "accessibility": 2,
    "buzz": 3,
    "significance": 3,
    "impactLevelOverride": "中",
    "officialConfirmed": true,
    "sources": [
      {
        "title": "Volleyball World VNL 2026 Finals match schedule",
        "url": "https://en.volleyballworld.com/volleyball/competitions/volleyball-nations-league/news/vnl-2026-finals-match-schedule-set-showdown-macao"
      },
      {
        "title": "TBS VNL女子2026 試合日程・結果",
        "url": "https://www.tbs.co.jp/volley-nationsleague/result/w.html"
      },
      {
        "title": "TBS VNL2026 放送情報",
        "url": "https://www.tbs.co.jp/volley-nationsleague/schedule/"
      }
    ]
  },
  {
    "id": "tenjin-matsuri-2026-yomiya",
    "title": "天神祭 宵宮",
    "startAt": "2026-07-24T07:45:00+09:00",
    "endAt": "2026-07-24T21:00:00+09:00",
    "broadcast": "現地イベント",
    "category": "祭り",
    "area": "大阪",
    "inPersonEvent": true,
    "liveReason": "大阪天満宮公式で24日の宵宮祭・鉾流神事・獅子舞氏地巡行が確認できる。日本三大祭の一つとして関西圏の話題性が高い",
    "trafficReason": "大阪市中心部の人流・交通混雑、夜の帰宅動線変化が関西圏の外出先選択に影響する可能性がある",
    "nationalReach": 3,
    "liveUrgency": 2,
    "accessibility": 1,
    "buzz": 2,
    "significance": 2,
    "impactLevelOverride": "中",
    "officialConfirmed": true,
    "sources": [
      {
        "title": "大阪天満宮 天神祭",
        "url": "https://osakatemmangu.or.jp/saijireki/tjm"
      },
      {
        "title": "大阪観光局 天神祭",
        "url": "https://osaka-info.jp/spot/tenjin-matsuri/"
      }
    ]
  },
  {
    "id": "gion-matsuri-2026-ato-junko",
    "title": "祇園祭 後祭 山鉾巡行・還幸祭",
    "startAt": "2026-07-24T09:30:00+09:00",
    "endAt": "2026-07-24T22:00:00+09:00",
    "broadcast": "現地イベント",
    "category": "祭り",
    "area": "京都",
    "inPersonEvent": true,
    "liveReason": "祇園祭の後祭山鉾巡行と還幸祭。京都中心部の終日人流・観光回遊が発生する",
    "trafficReason": "京都中心部の交通規制・観光回遊・夜の帰宅混雑が、関西圏の移動や外出先選択に影響する可能性がある",
    "nationalReach": 2,
    "liveUrgency": 3,
    "accessibility": 1,
    "buzz": 2,
    "significance": 3,
    "impactLevelOverride": "中",
    "officialConfirmed": true,
    "sources": [
      {
        "title": "GionFestival.org Gion Festival overview",
        "url": "https://www.gionfestival.org/"
      },
      {
        "title": "京都観光Navi 祇園祭",
        "url": "https://ja.kyoto.travel/event/major/gion/"
      }
    ]
  },
  {
    "id": "fuji-rock-festival-2026",
    "title": "FUJI ROCK FESTIVAL '26",
    "startAt": "2026-07-24T11:00:00+09:00",
    "endAt": "2026-07-26T23:00:00+09:00",
    "broadcast": "現地イベント・公式配信有無は直前確認",
    "category": "音楽フェス",
    "area": "新潟",
    "inPersonEvent": true,
    "liveReason": "国内最大級の野外音楽フェス。7月24日から26日の開催で、Kaze Fujii、Kendrick Lamarなどの出演情報が公開され話題化しやすい",
    "trafficReason": "現地影響は新潟中心。全国的には出演者・配信・SNS話題による間接影響として扱い、神戸への直接影響は過大評価しない",
    "nationalReach": 2,
    "liveUrgency": 2,
    "accessibility": 1,
    "buzz": 3,
    "significance": 2,
    "impactLevelOverride": "中",
    "officialConfirmed": true,
    "sources": [
      {
        "title": "FUJI ROCK FESTIVAL '26 公式サイト",
        "url": "https://www.fujirockfestival.com/"
      },
      {
        "title": "Fuji Rock Festival 2026 summary",
        "url": "https://de.wikipedia.org/wiki/Fuji_Rock_Festival"
      }
    ]
  },
  {
    "id": "tenjin-matsuri-2026-hongu",
    "title": "天神祭 本宮・奉納花火",
    "startAt": "2026-07-25T15:30:00+09:00",
    "endAt": "2026-07-25T21:30:00+09:00",
    "broadcast": "テレビ大阪 18:58から生中継・eo光テレビ 16:00から陸渡御生中継・現地イベント",
    "category": "祭り・花火",
    "area": "大阪",
    "inPersonEvent": true,
    "liveReason": "大阪天満宮公式で25日の本宮、陸渡御、船渡御、奉納花火が確認できる。日本三大祭の一つで、関西圏の人流影響が大きい",
    "trafficReason": "大阪市中心部の夕方以降の人流・交通混雑、花火終了後の帰宅混雑が、関西圏の移動と外出先選択に影響する可能性がある",
    "nationalReach": 3,
    "liveUrgency": 3,
    "accessibility": 1,
    "buzz": 3,
    "significance": 3,
    "impactLevelOverride": "中",
    "officialConfirmed": true,
    "sources": [
      {
        "title": "大阪天満宮 天神祭",
        "url": "https://osakatemmangu.or.jp/saijireki/tjm"
      },
      {
        "title": "大阪観光局 天神祭",
        "url": "https://osaka-info.jp/spot/tenjin-matsuri/"
      },
      {
        "title": "テレビ大阪 天神祭 生中継 2026",
        "url": "https://www.tv-osaka.co.jp/tenjin2026/"
      }
    ]
  },
  {
    "id": "sumidagawa-hanabi-2026",
    "title": "隅田川花火大会",
    "startAt": "2026-07-25T19:00:00+09:00",
    "endAt": "2026-07-25T20:30:00+09:00",
    "broadcast": "テレビ東京系列 18:30から独占生中継・TVer／YouTube裏生配信・現地イベント",
    "category": "花火",
    "area": "東京",
    "inPersonEvent": true,
    "liveReason": "公式サイトで令和8年7月25日19時開催予定が確認できる東京の代表的花火大会。神戸への直接影響は小さいが、テレビ放送・SNS・ニュースで全国話題になりやすい",
    "trafficReason": "現地の人流影響は東京中心。神戸ではテレビ放送やSNSで話題になる場合のみ、客足への間接影響を確認する",
    "nationalReach": 3,
    "liveUrgency": 2,
    "accessibility": 3,
    "buzz": 3,
    "significance": 3,
    "impactLevelOverride": "中",
    "officialConfirmed": true,
    "sources": [
      {
        "title": "隅田川花火大会 公式Webサイト",
        "url": "https://www.sumidagawa-hanabi.com/"
      },
      {
        "title": "令和8年 第49回 隅田川花火大会 実施計画概要",
        "url": "https://www.sumidagawa-hanabi.com/assets/pdf/%E4%BB%A4%E5%92%8C8%E5%B9%B4(%E7%AC%AC49%E5%9B%9E)%E5%AE%9F%E6%96%BD%E8%A8%88%E7%94%BB%E6%A6%82%E8%A6%81.pdf"
      },
      {
        "title": "テレビ東京 独占生中継 隅田川花火大会 2026",
        "url": "https://www.tv-tokyo.co.jp/hanabi2026/"
      }
    ]
  },
  {
    "id": "sumo-july-basho-2026-final-day",
    "title": "大相撲七月場所 千秋楽",
    "startAt": "2026-07-26T15:05:00+09:00",
    "endAt": "2026-07-26T18:00:00+09:00",
    "broadcast": "NHK総合・NHK BSなど（番組表確認）",
    "category": "スポーツ中継",
    "area": "全国",
    "liveReason": "日本相撲協会公式で七月場所が7月12日から26日までIGアリーナ開催と確認できる。千秋楽は優勝争いと表彰でリアルタイム視聴の動機が強い",
    "trafficReason": "日曜夕方のテレビ視聴・結果確認で、夕方の外出や買い物時間が前後する可能性を確認する",
    "nationalReach": 2,
    "liveUrgency": 2,
    "accessibility": 3,
    "buzz": 2,
    "significance": 3,
    "officialConfirmed": true,
    "sources": [
      {
        "title": "日本相撲協会 2026 Grand Tournament Schedule",
        "url": "https://www.sumo.or.jp/EnTicket/year_schedule/"
      },
      {
        "title": "NHK 大相撲中継",
        "url": "https://www.nhk.jp/p/ts/JY7XMMG241/"
      }
    ]
  },
  {
    "id": "vnl-men-2026-final-round",
    "title": "VNL男子2026 ファイナルラウンド",
    "startAt": "2026-07-29T18:00:00+09:00",
    "endAt": "2026-08-02T23:00:00+09:00",
    "broadcast": "VBTV・国内放送は番組表確認",
    "category": "スポーツ中継",
    "area": "全国",
    "liveReason": "男子バレーボールの国際大会決勝ラウンド。日本が進出した場合はSNS・ニュース確認とリアルタイム視聴が起きやすい",
    "trafficReason": "日本代表の進出状況と放送有無で影響が大きく変わるため、確定カード発表後に更新する。現時点では候補扱いで過大評価しない",
    "nationalReach": 2,
    "liveUrgency": 2,
    "accessibility": 1,
    "buzz": 2,
    "significance": 2,
    "impactLevelOverride": "小",
    "officialConfirmed": false,
    "sources": [
      {
        "title": "2026 FIVB Men's Volleyball Nations League",
        "url": "https://en.wikipedia.org/wiki/2026_FIVB_Men%27s_Volleyball_Nations_League"
      }
    ]
  },
  {
    "id": "summer-koshien-2026-opening",
    "title": "夏の甲子園2026 開幕",
    "startAt": "2026-08-05T16:00:00+09:00",
    "endAt": "2026-08-05T20:00:00+09:00",
    "broadcast": "NHK・ABCテレビなど（番組表確認）",
    "category": "スポーツ中継・現地イベント",
    "area": "兵庫",
    "inPersonEvent": true,
    "liveReason": "第108回全国高校野球選手権大会の開幕日。関西ローカルと全国ニュースで扱われやすく、開会式と初戦の視聴・結果確認が起きやすい",
    "trafficReason": "甲子園周辺と阪神沿線の来場混雑が中心。神戸では高校野球の話題化、テレビ視聴、阪神間の移動混雑を確認する",
    "nationalReach": 3,
    "liveUrgency": 2,
    "accessibility": 3,
    "buzz": 2,
    "significance": 3,
    "impactLevelOverride": "中",
    "officialConfirmed": false,
    "sources": [
      {
        "title": "第108屆全國高等學校棒球錦標賽",
        "url": "https://zh.wikipedia.org/wiki/%E7%AC%AC108%E5%B1%86%E5%85%A8%E5%9C%8B%E9%AB%98%E7%AD%89%E5%AD%B8%E6%A0%A1%E6%A3%92%E7%90%83%E9%8C%A6%E6%A8%99%E8%B3%BD"
      }
    ]
  },
  {
    "id": "awa-odori-tokushima-2026",
    "title": "徳島市阿波おどり",
    "startAt": "2026-08-12T18:00:00+09:00",
    "endAt": "2026-08-15T22:30:00+09:00",
    "showEachDay": true,
    "broadcast": "現地イベント",
    "category": "祭り",
    "area": "徳島",
    "inPersonEvent": true,
    "liveReason": "毎年8月12日から15日に徳島市で開催される大型盆踊りイベント。お盆時期の旅行・帰省・SNS話題化と重なりやすい",
    "trafficReason": "直接影響は徳島中心。関西からの旅行・帰省・高速バスやフェリー利用、連休中の外出先選択への間接影響を確認する",
    "nationalReach": 2,
    "liveUrgency": 2,
    "accessibility": 1,
    "buzz": 2,
    "significance": 3,
    "impactLevelOverride": "小",
    "officialConfirmed": false,
    "sources": [
      {
        "title": "Awa Odori",
        "url": "https://de.wikipedia.org/wiki/Awa_Odori"
      },
      {
        "title": "阿波舞",
        "url": "https://zh.wikipedia.org/wiki/%E9%98%BF%E6%B3%A2%E8%88%9E"
      }
    ]
  },
  {
    "id": "comic-market-108",
    "title": "コミックマーケット108",
    "startAt": "2026-08-15T10:00:00+09:00",
    "endAt": "2026-08-16T16:00:00+09:00",
    "showEachDay": true,
    "broadcast": "現地イベント",
    "category": "大型イベント",
    "area": "東京",
    "inPersonEvent": true,
    "liveReason": "東京ビッグサイト開催の大型同人誌即売会。SNSでの話題量が大きく、参加者の遠征・通販・関連消費が発生しやすい",
    "trafficReason": "直接影響は東京中心。神戸では遠征客、SNS話題、関連商品のオンライン確認など間接影響として確認する",
    "nationalReach": 2,
    "liveUrgency": 2,
    "accessibility": 1,
    "buzz": 3,
    "significance": 2,
    "impactLevelOverride": "小",
    "officialConfirmed": false,
    "sources": [
      {
        "title": "Comiket",
        "url": "https://en.wikipedia.org/wiki/Comiket"
      }
    ]
  },
  {
    "id": "kyoto-gozan-okuribi-2026",
    "title": "京都五山送り火",
    "startAt": "2026-08-16T20:00:00+09:00",
    "endAt": "2026-08-16T20:45:00+09:00",
    "broadcast": "現地イベント・中継は番組表確認",
    "category": "祭り",
    "area": "京都",
    "inPersonEvent": true,
    "liveReason": "毎年8月16日夜に京都で行われる伝統行事。お盆最終盤の観光・帰省動線と重なり、関西圏のニュースでも扱われやすい",
    "trafficReason": "京都市内の夜間人流・観光回遊・帰宅混雑が中心。神戸では関西圏の外出先選択や帰宅時間の変化を確認する",
    "nationalReach": 2,
    "liveUrgency": 2,
    "accessibility": 1,
    "buzz": 2,
    "significance": 3,
    "impactLevelOverride": "中",
    "officialConfirmed": false,
    "sources": [
      {
        "title": "Gozan no Okuribi",
        "url": "https://en.wikipedia.org/wiki/Gozan_no_Okuribi"
      },
      {
        "title": "五山送火",
        "url": "https://zh.wikipedia.org/wiki/%E4%BA%94%E5%B1%B1%E9%80%81%E7%81%AB"
      }
    ]
  },
  {
    "id": "summer-koshien-2026-final",
    "title": "夏の甲子園2026 決勝",
    "startAt": "2026-08-22T10:00:00+09:00",
    "endAt": "2026-08-22T13:00:00+09:00",
    "broadcast": "NHK・ABCテレビなど（番組表確認）",
    "category": "スポーツ中継・現地イベント",
    "area": "兵庫",
    "inPersonEvent": true,
    "liveReason": "夏の甲子園決勝。全国的な注目度が高く、出場校次第でテレビ視聴・SNS確認・ニュース確認が大きくなる",
    "trafficReason": "甲子園周辺と阪神沿線の来場混雑が中心。神戸では午前から昼のテレビ視聴、結果確認、阪神間移動の混雑を確認する",
    "nationalReach": 3,
    "liveUrgency": 3,
    "accessibility": 3,
    "buzz": 3,
    "significance": 3,
    "impactLevelOverride": "中",
    "officialConfirmed": false,
    "sources": [
      {
        "title": "第108屆全國高等學校棒球錦標賽",
        "url": "https://zh.wikipedia.org/wiki/%E7%AC%AC108%E5%B1%86%E5%85%A8%E5%9C%8B%E9%AB%98%E7%AD%89%E5%AD%B8%E6%A0%A1%E6%A3%92%E7%90%83%E9%8C%A6%E6%A8%99%E8%B3%BD"
      }
    ]
  },
  {
    "id": "twenty-four-hour-tv-2026",
    "title": "24時間テレビ2026",
    "startAt": "2026-08-29T18:30:00+09:00",
    "endAt": "2026-08-30T20:54:00+09:00",
    "showEachDay": true,
    "broadcast": "日本テレビ系列",
    "category": "テレビ特番",
    "area": "全国",
    "liveReason": "日本テレビ系列の大型長時間特番。土曜夜から日曜夜にかけて放送され、出演者・企画・チャリティー企画でSNS確認が起きやすい",
    "trafficReason": "在宅視聴や話題企画の確認で、土曜夜から日曜夜の外出時間が前後する可能性を確認する",
    "nationalReach": 3,
    "liveUrgency": 2,
    "accessibility": 3,
    "buzz": 2,
    "significance": 2,
    "officialConfirmed": false,
    "sources": [
      {
        "title": "24時間テレビ 日本テレビ",
        "url": "https://www.ntv.co.jp/24h/"
      },
      {
        "title": "24小時電視 愛心救地球",
        "url": "https://zh.wikipedia.org/wiki/24%E5%B0%8F%E6%99%82%E9%9B%BB%E8%A6%96_%E3%80%8C%E6%84%9B%E5%BF%83%E6%95%91%E5%9C%B0%E7%90%83%E3%80%8D"
      }
    ]
  }
]
